fimdp/__init__.py
fimdp/core.py
fimdp/distribution.py
fimdp/dot.py
fimdp/energy_solvers.py
fimdp/explicit.py
fimdp/io.py
fimdp/labeled.py
fimdp/mincap_solvers.py
fimdp/objectives.py
fimdp/utils.py
fimdp-2.0.dist-info/LICENSE
fimdp-2.0.dist-info/METADATA
fimdp-2.0.dist-info/WHEEL
fimdp-2.0.dist-info/top_level.txt
fimdp-2.0.dist-info/RECORD
