Metadata-Version: 2.1
Name: fimdp
Version: 2.0
Summary: Package with tools for Resource-constrained Markov Decision Processes
Home-page: https://github.com/FiMDP/FiMDP
Author: Fanda Blahoudek
Author-email: fandikb+dev@gmail.com
License: MIT
Keywords: polynomial-time,buchi-objective,agent,cmdp,controller-synthesis,formal-methods
Platform: UNKNOWN
Requires-Python: >=3.6.0
